Metadata-Version: 2.1
Name: dj-cref
Version: 0.0.8
Summary: The django generic view output unit
Home-page: https://github.com/Canon11/dj-cref
Author: Kazuma Murata
Author-email: mrt014kzm@gmail.com
License: MIT
Keywords: django,generic,output
Platform: UNKNOWN
Classifier: Programming Language :: Python :: 3.6
